fzfdirhist/__init__.py
fzfdirhist/__main__.py
fzfdirhist/fzfdirhist.py
fzf_dirhistory-0.1.1.dist-info/LICENSE
fzf_dirhistory-0.1.1.dist-info/METADATA
fzf_dirhistory-0.1.1.dist-info/WHEEL
fzf_dirhistory-0.1.1.dist-info/top_level.txt
fzf_dirhistory-0.1.1.dist-info/RECORD
