Metadata-Version: 2.1
Name: fzf-dirhistory
Version: 0.1.1
Summary: Log recently visited directories for FZF
Home-page: https://github.com/ojroques/fzf-dirhistory
Author: Olivier Roques
Author-email: olivier@oroques.dev
License: UNKNOWN
Platform: UNKNOWN
Classifier: Programming Language :: Python :: 3
Classifier: License :: OSI Approved :: GNU Lesser General Public License v2 or later (LGPLv2+)
Classifier: Operating System :: Unix
Classifier: Topic :: Terminals
Requires-Python: >=3.5
License-File: LICENSE
